hellodoycode/__init__.py
hellodoycode/helloworld1/__init__.py
hellodoycode/helloworld2/__init__.py
hellodoycode/helloworld3/__init__.py
hellodoycode-0.0.2.dist-info/LICENSE
hellodoycode-0.0.2.dist-info/METADATA
hellodoycode-0.0.2.dist-info/WHEEL
hellodoycode-0.0.2.dist-info/top_level.txt
hellodoycode-0.0.2.dist-info/RECORD
