Metadata-Version: 2.1
Name: hellodoycode
Version: 0.0.2
Summary: The first installation of python.
Home-page: UNKNOWN
Author: Dong
Author-email: dongyuncheng1991@gmail.com
License: UNKNOWN
Platform: UNKNOWN
Classifier: Programming Language :: Python :: 3
Classifier: License :: OSI Approved :: MIT License
Classifier: Operating System :: OS Independent
